pulumi_rke/__init__.py
pulumi_rke/_inputs.py
pulumi_rke/_utilities.py
pulumi_rke/cluster.py
pulumi_rke/outputs.py
pulumi_rke/provider.py
pulumi_rke/pulumi-plugin.json
pulumi_rke/py.typed
pulumi_rke/config/__init__.py
pulumi_rke/config/__init__.pyi
pulumi_rke/config/vars.py
pulumi_rke-3.6.0.dist-info/METADATA
pulumi_rke-3.6.0.dist-info/WHEEL
pulumi_rke-3.6.0.dist-info/top_level.txt
pulumi_rke-3.6.0.dist-info/RECORD
